<?xml version="1.0" encoding="utf-8" ?>
<XnaContent>
  <Asset Type="System.Collections.Generic.List[ImportTemplates.BlockTemplate]">
    <Item>
      <Position>4,1,1</Position>
      <Color>0,0,0,255</Color>
    </Item>
    <Item>
      <Position>4,1,2</Position>
      <Color>0,0,0,255</Color>
    </Item>
    <Item>
      <Position>4,1,3</Position>
      <Color>0,0,0,255</Color>
    </Item>
    <Item>
      <Position>4,2,1</Position>
      <Color>0,0,0,255</Color>
    </Item>
    <Item>
      <Position>4,2,2</Position>
      <Color>0,0,0,255</Color>
    </Item>
    <Item>
      <Position>4,2,3</Position>
      <Color>0,0,0,255</Color>
    </Item>
  </Asset>
</XnaContent>
